expotower/__init__.py
expotower/__main__.py
expotower/core.py
expotower-0.1.1.dist-info/licenses/LICENSE.txt
expotower-0.1.1.dist-info/METADATA
expotower-0.1.1.dist-info/WHEEL
expotower-0.1.1.dist-info/entry_points.txt
expotower-0.1.1.dist-info/top_level.txt
expotower-0.1.1.dist-info/RECORD
