Metadata-Version: 2.4
Name: expotower
Version: 0.1.1
Summary: A simple library for computing exponential towers
Author-email: YourName <you@example.com>
License: MIT
Keywords: math,exponentiation,power tower,tetration
Classifier: Programming Language :: Python :: 3
Classifier: License :: OSI Approved :: MIT License
Classifier: Topic :: Scientific/Engineering :: Mathematics
Requires-Python: >=3.7
License-File: LICENSE.txt
Dynamic: license-file
